robotars
