Metadata-Version: 1.0
Name: robotars
Version: 0.2
Summary: a fun little app for creating robot avatars from the Robohash API
Home-page: http://github.com/eldarion/robotars
Author: Eldarion
Author-email: paltman@eldarion.com
License: BSD
Platform: UNKNOWN
Classifier: Development Status :: 3 - Alpha
Classifier: Environment :: Web Environment
Classifier: Intended Audience :: Developers
Classifier: License :: OSI Approved :: BSD License
Classifier: Operating System :: OS Independent
Classifier: Programming Language :: Python
Classifier: Framework :: Django
